<?xml version="1.0" encoding="utf-8"?>
<h:html xmlns="http://www.w3.org/2002/xforms" xmlns:h="http://www.w3.org/1999/xhtml" xmlns:ev="http://www.w3.org/2001/xml-events" xmlns:xsd="http://www.w3.org/2001/XMLSchema" xmlns:jr="http://openrosa.org/javarosa">
  <!-- ****** -->
  <!--FAIMS UI Schema generated by Heurist Vsn 3.1.4, Saturday 9th of November 2013 04:03:14 AM-->
  <!--Database: hdb_test_NZG   Heurist user:guest guest-->
  <!-- ****** -->
  <h:head>
    <h:title>hdb test NZG</h:title>
    <!--model lists user interface tabgroups, tabs and content of tabs-->
    <model>
      <instance>
        <faims id="hdb_test_NZG">
          <style>
            <orientation>
              <orientation/>
            </orientation>
            <even>
              <layout_weight/>
            </even>
          </style>
          <user>
            <usertab>
              <users/>
            </usertab>
          </user>
          <!--control tabgroup that contains button to manipulate entities: load, list, create-->
          <control>
            <buttonholder>
              <GeoSample/>
            </buttonholder>
            <map>
              <map/>
              <mapContainer>
                <child0>
                  <zoomGPS/>
                </child0>
                <child1>
                  <clear/>
                </child1>
                <child2>
                  <create/>
                </child2>
              </mapContainer>
            </map>
            <data>
              <GeoSampleList/>
              <GeoSampleLoad/>
            </data>
            <gps>
              <connectexternal/>
              <connectinternal/>
              <startsync/>
              <stopsync/>
              <startTimeLog/>
              <startDistanceLog/>
              <stopTrackLog/>
            </gps>
          </control>
          <!--list of tabgroups for entities-->
          <!--ArchEnt / Record Type: GEOSAMPLE-->
          <GeoSample>
            <GeoSample_GeneralInformation>
              <Name_Title/>
              <Timestamp/>
            </GeoSample_GeneralInformation>
            <GeoSample_Top_Sample>
              <Top_Sample_ID/>
              <Collected_/>
              <Regolith/>
              <Horizon_A/>
              <Upper_Depth_A/>
              <Bottom_Depth_A/>
              <Dom_Size_A/>
              <Fraction_A/>
              <State_A/>
            </GeoSample_Top_Sample>
            <GeoSample_Bottom_Sample>
              <Bottom_Sample_ID/>
              <Bottom_Sample_Collected_/>
              <Regolith_B/>
              <Horizon_B/>
              <Upper_Depth_B/>
              <Bottom_Depth_B/>
              <Dom_Size_B/>
              <Fraction_B/>
              <State_B/>
            </GeoSample_Bottom_Sample>
            <GeoSample_Rock_Information>
              <Slope/>
              <Rock_Type/>
              <Landuse/>
              <Contamination/>
              <Comments/>
              <Photo_Comments/>
              <Thumbnail_image/>
              <attachThumbnail_image/>
              <Update/>
              <Delete/>
            </GeoSample_Rock_Information>
          </GeoSample>
        </faims>
      </instance>
      <!--list of numeric and blocktext(memo) attributes(fields)-->
      <bind nodeset="/faims/GeoSample/GeoSample_Rock_Information/Comments" type="string"/>
    </model>
  </h:head>
  <h:body>
    <!--Describes controls for each tabgroup and its nested tabs-->
    <group ref="style">
      <label/>
      <group ref="orientation">
        <label/>
        <input ref="orientation">
          <label>horizontal</label>
        </input>
      </group>
      <group ref="even">
        <label/>
        <input ref="layout_weight">
          <label>1</label>
        </input>
      </group>
    </group>
    <group ref="user">
      <label>{User_List}</label>
      <group ref="usertab" faims_scrollable="false">
        <label>{User_List}</label>
        <select1 appearance="compact" ref="users">
          <label>{Users}:</label>
          <item>
            <label>placeholder</label>
            <value>placeholder</value>
          </item>
        </select1>
      </group>
    </group>
    <group ref="control">
      <label>Maps and Controls</label>
      <group faims_scrollable="false" ref="map">
        <label>Map</label>
        <input faims_certainty="false" faims_map="true" ref="map">
          <label/>
        </input>
      </group>
      <group faims_style="orientation" ref="mapContainer">
        <label/>
        <group faims_style="even" ref="child0">
          <label/>
          <trigger ref="zoomGPS">
            <label>CenterMe</label>
          </trigger>
        </group>
        <group faims_style="even" ref="child1">
          <label/>
          <trigger ref="clear">
            <label>Remove</label>
          </trigger>
        </group>
        <group faims_style="even" ref="child2">
          <label/>
          <trigger ref="create">
            <label>Create</label>
          </trigger>
        </group>
      </group>
    </group>
    <group ref="data" faims_scrollable="false">
      <label>Saved Features</label>
      <select1 faims_annotation="false" faims_certainty="false" ref="RS_FeatureList" appearance="compact">
        <label>Saved Remote Sensing Features</label>
        <item>
          <label>placeholder</label>
          <value>placeholder</value>
        </item>
      </select1>
    </group>
    <group ref="gps">
      <label>Control</label>
      <trigger ref="connectexternal">
        <label>Connect To External GPS</label>
      </trigger>
      <trigger ref="connectinternal">
        <label>Connect To Internal GPS</label>
      </trigger>
      <trigger ref="startsync">
        <label>Start Synching</label>
      </trigger>
      <trigger ref="stopsync">
        <label>Stop Synching</label>
      </trigger>
      <trigger ref="startTimeLog">
        <label>Start Time Log</label>
      </trigger>
      <trigger ref="startDistanceLog">
        <label>Start Distance Log</label>
      </trigger>
      <trigger ref="stopTrackLog">
        <label>Stop Track Log</label>
      </trigger>
    </group>
    <!--GEOSAMPLE-->
    <group ref="GeoSample" faims_archent_type="GeoSample">
      <label>{GeoSample}</label>
      <group ref="GeoSample_GeneralInformation">
        <label>{Soil_core_collected_by_the_geochemistry_team}</label>
        <input ref="Name_Title" faims_attribute_name="Name / Title" faims_certainty="false" faims_attribute_type="freetext" faims_read_only="false">
          <label>{Site_ID}</label>
        </input>
        <input ref="Timestamp" faims_attribute_name="Timestamp" faims_certainty="true" faims_attribute_type="freetext" faims_read_only="false">
          <label>{Timestamp}</label>
        </input>
      </group>
      <group ref="GeoSample_Top_Sample">
        <label>{Top_Sample}</label>
        <input ref="Top_Sample_ID" faims_attribute_name="Top Sample ID" faims_certainty="true" faims_attribute_type="freetext" faims_read_only="false">
          <label>{Top_Sample_ID}</label>
        </input>
        <!--We would like to see Radiogroup-->
        <select1 ref="Collected_" faims_attribute_name="Collected?" faims_certainty="true" appearance="full" faims_attribute_type="vocab" faims_read_only="false">
          <label>{Top_Sample_Collected?}</label>
          <item>
            <label>placeholder</label>
            <value>placeholder</value>
          </item>
        </select1>
        <!--We would like to see Radiogroup-->
        <select1 ref="Regolith" faims_attribute_name="Regolith" faims_certainty="true" appearance="full" faims_attribute_type="vocab" faims_read_only="false">
          <label>{Regolith_A}</label>
          <item>
            <label>placeholder</label>
            <value>placeholder</value>
          </item>
        </select1>
        <!--We would like to see Radiogroup-->
        <select1 ref="Horizon_A" faims_attribute_name="Horizon A" faims_certainty="true" appearance="full" faims_attribute_type="vocab" faims_read_only="false">
          <label>{Horizon_A}</label>
          <item>
            <label>placeholder</label>
            <value>placeholder</value>
          </item>
        </select1>
        <!--We would like to see Radiogroup-->
        <select1 ref="Upper_Depth_A" faims_attribute_name="Upper Depth A" faims_certainty="true" appearance="full" faims_attribute_type="vocab" faims_read_only="false">
          <label>{Upper_Depth_A}</label>
          <item>
            <label>placeholder</label>
            <value>placeholder</value>
          </item>
        </select1>
        <!--We would like to see Radiogroup-->
        <select1 ref="Bottom_Depth_A" faims_attribute_name="Bottom Depth A" faims_certainty="true" appearance="full" faims_attribute_type="vocab" faims_read_only="false">
          <label>{Bottom_Depth_A}</label>
          <item>
            <label>placeholder</label>
            <value>placeholder</value>
          </item>
        </select1>
        <!--We would like to see Dropdown-->
        <select1 ref="Dom_Size_A" faims_attribute_name="Dom Size A" faims_certainty="true" faims_attribute_type="vocab" faims_read_only="false">
          <label>{Dom_Size_A}</label>
          <item>
            <label>placeholder</label>
            <value>placeholder</value>
          </item>
        </select1>
        <!--We would like to see Radiogroup-->
        <select1 ref="Fraction_A" faims_attribute_name="Fraction A" faims_certainty="true" appearance="full" faims_attribute_type="vocab" faims_read_only="false">
          <label>{Fraction_A}</label>
          <item>
            <label>placeholder</label>
            <value>placeholder</value>
          </item>
        </select1>
        <!--We would like to see Radiogroup-->
        <select1 ref="State_A" faims_attribute_name="State A" faims_certainty="true" appearance="full" faims_attribute_type="vocab" faims_read_only="false">
          <label>{State_A}</label>
          <item>
            <label>placeholder</label>
            <value>placeholder</value>
          </item>
        </select1>
      </group>
      <group ref="GeoSample_Bottom_Sample">
        <label>{Bottom_Sample}</label>
        <input ref="Bottom_Sample_ID" faims_attribute_name="Bottom Sample ID" faims_certainty="true" faims_attribute_type="freetext" faims_read_only="false">
          <label>{Bottom_Sample_ID}</label>
        </input>
        <!--We would like to see Radiogroup-->
        <select1 ref="Bottom_Sample_Collected_" faims_attribute_name="Bottom Sample Collected?" faims_certainty="true" appearance="full" faims_attribute_type="vocab" faims_read_only="false">
          <label>{Bottom_Sample_Collected?}</label>
          <item>
            <label>placeholder</label>
            <value>placeholder</value>
          </item>
        </select1>
        <!--We would like to see Radiogroup-->
        <select1 ref="Regolith_B" faims_attribute_name="Regolith B" faims_certainty="true" appearance="full" faims_attribute_type="vocab" faims_read_only="false">
          <label>{Regolith_B}</label>
          <item>
            <label>placeholder</label>
            <value>placeholder</value>
          </item>
        </select1>
        <!--We would like to see Radiogroup-->
        <select1 ref="Horizon_B" faims_attribute_name="Horizon B" faims_certainty="true" appearance="full" faims_attribute_type="vocab" faims_read_only="false">
          <label>{Horizon_B}</label>
          <item>
            <label>placeholder</label>
            <value>placeholder</value>
          </item>
        </select1>
        <!--We would like to see Radiogroup-->
        <select1 ref="Upper_Depth_B" faims_attribute_name="Upper Depth B" faims_certainty="true" appearance="full" faims_attribute_type="vocab" faims_read_only="false">
          <label>{Upper_Depth_B}</label>
          <item>
            <label>placeholder</label>
            <value>placeholder</value>
          </item>
        </select1>
        <!--We would like to see Radiogroup-->
        <select1 ref="Bottom_Depth_B" faims_attribute_name="Bottom Depth B" faims_certainty="true" appearance="full" faims_attribute_type="vocab" faims_read_only="false">
          <label>{Bottom_Depth_B}</label>
          <item>
            <label>placeholder</label>
            <value>placeholder</value>
          </item>
        </select1>
        <!--We would like to see Dropdown-->
        <select1 ref="Dom_Size_B" faims_attribute_name="Dom Size B" faims_certainty="true" faims_attribute_type="vocab" faims_read_only="false">
          <label>{Dom_Size_B}</label>
          <item>
            <label>placeholder</label>
            <value>placeholder</value>
          </item>
        </select1>
        <!--We would like to see Radiogroup-->
        <select1 ref="Fraction_B" faims_attribute_name="Fraction B" faims_certainty="true" appearance="full" faims_attribute_type="vocab" faims_read_only="false">
          <label>{Fraction_B}</label>
          <item>
            <label>placeholder</label>
            <value>placeholder</value>
          </item>
        </select1>
        <!--We would like to see Radiogroup-->
        <select1 ref="State_B" faims_attribute_name="State B" faims_certainty="true" appearance="full" faims_attribute_type="vocab" faims_read_only="false">
          <label>{State_B}</label>
          <item>
            <label>placeholder</label>
            <value>placeholder</value>
          </item>
        </select1>
      </group>
      <group ref="GeoSample_Rock_Information">
        <label>{Rock_Information}</label>
        <!--We would like to see Radiogroup-->
        <select1 ref="Slope" faims_attribute_name="Slope" faims_certainty="true" appearance="full" faims_attribute_type="vocab" faims_read_only="false">
          <label>{Slope}</label>
          <item>
            <label>placeholder</label>
            <value>placeholder</value>
          </item>
        </select1>
        <input ref="Rock_Type" faims_attribute_name="Rock Type" faims_certainty="true" faims_attribute_type="freetext" faims_read_only="false">
          <label>{Rock_Type}</label>
        </input>
        <!--We would like to see Dropdown-->
        <select1 ref="Landuse" faims_attribute_name="Landuse" faims_certainty="true" faims_attribute_type="vocab" faims_read_only="false">
          <label>{Landuse}</label>
          <item>
            <label>placeholder</label>
            <value>placeholder</value>
          </item>
        </select1>
        <input ref="Contamination" faims_attribute_name="Contamination" faims_certainty="true" faims_attribute_type="freetext" faims_read_only="false">
          <label>{Contamination}</label>
        </input>
        <input ref="Comments" faims_attribute_name="Comments" faims_certainty="true" faims_attribute_type="freetext" faims_read_only="false">
          <label>{Site_Comments}</label>
        </input>
        <input ref="Photo_Comments" faims_attribute_name="Photo Comments" faims_certainty="true" faims_attribute_type="freetext" faims_read_only="false">
          <label>{Photo_Comments}</label>
        </input>
        <select ref="Thumbnail_image" faims_attribute_name="Thumbnail image" faims_certainty="true" faims_attribute_type="freetext" faims_sync="true" type="camera" faims_annotation="false">
          <label>{Thumbnail_image}</label>
          <item>
            <label>placeholder</label>
            <value>placeholder</value>
          </item>
        </select>
        <trigger ref="attachThumbnail_image">
          <label>Take Picture</label>
        </trigger>
        <trigger ref="Update">
          <label>{Save.Record}</label>
        </trigger>
        <trigger ref="Delete">
          <label>{Delete.Record}</label>
        </trigger>
      </group>
    </group>
  </h:body>
</h:html>
